pystitch/__init__.py
pystitch/cli.py
pystitch/process.py
pystitch/pystitch.py
pystitch/tests.py
stitchpy-0.0.4.dist-info/METADATA
stitchpy-0.0.4.dist-info/WHEEL
stitchpy-0.0.4.dist-info/top_level.txt
stitchpy-0.0.4.dist-info/RECORD
